{
  "Mean": {
    "confidence_interval": {
      "confidence_level": 0.95,
      "lower_bound": 44.334615,
      "upper_bound": 44.627414
    },
    "point_estimate": 44.476683,
    "standard_error": 0.074533
  },
  "Median": {
    "confidence_interval": {
      "confidence_level": 0.95,
      "lower_bound": 44.107245,
      "upper_bound": 44.343214
    },
    "point_estimate": 44.193171,
    "standard_error": 0.064587
  },
  "MedianAbsDev": {
    "confidence_interval": {
      "confidence_level": 0.95,
      "lower_bound": 0.366524,
      "upper_bound": 0.736513
    },
    "point_estimate": 0.514367,
    "standard_error": 0.088068
  },
  "Slope": {
    "confidence_interval": {
      "confidence_level": 0.95,
      "lower_bound": 44.001838,
      "upper_bound": 44.143829
    },
    "point_estimate": 44.07004,
    "standard_error": 0.03618
  },
  "StdDev": {
    "confidence_interval": {
      "confidence_level": 0.95,
      "lower_bound": 0.620559,
      "upper_bound": 0.859011
    },
    "point_estimate": 0.746658,
    "standard_error": 0.060722
  }
}